my_package/__init__.py
my_package/bpgtask.py
my_package/main.py
my_package/my_module.py
my_package/testable_code/example.py
bpgtask-0.1.4.dist-info/METADATA
bpgtask-0.1.4.dist-info/WHEEL
bpgtask-0.1.4.dist-info/RECORD
