Metadata-Version: 2.1
Name: bpgtask
Version: 0.1.4
Summary: 
Author: Yu Chang
Author-email: yu.chang@rokt.com
Requires-Python: >=3.12,<3.13
Classifier: Programming Language :: Python :: 3
Classifier: Programming Language :: Python :: 3.12
Requires-Dist: flytekit (>=1.11.0,<2.0.0)
Requires-Dist: requests (>=2.31.0,<3.0.0)
